request_session/__init__.py
request_session/_compat.py
request_session/exceptions.py
request_session/protocols.py
request_session/request_session.py
request_session/utils.py
request_session-0.16.4.dist-info/LICENSE
request_session-0.16.4.dist-info/METADATA
request_session-0.16.4.dist-info/WHEEL
request_session-0.16.4.dist-info/top_level.txt
request_session-0.16.4.dist-info/RECORD
