Metadata-Version: 2.1
Name: request-session
Version: 0.16.4
Summary: Python HTTP requests on steroids
Home-page: https://github.com/kiwicom/request-session
Author: Kiwi.com platform team
Author-email: platform@kiwi.com
License: UNKNOWN
Platform: UNKNOWN
Classifier: Development Status :: 4 - Beta
Classifier: Operating System :: OS Independent
Classifier: Topic :: Internet :: WWW/HTTP
Classifier: Programming Language :: Python :: 3.9
Classifier: Programming Language :: Python :: 3.10
Classifier: Programming Language :: Python :: 3.11
Classifier: Intended Audience :: Developers
License-File: LICENSE
Requires-Dist: requests
Requires-Dist: simplejson
Requires-Dist: structlog
Provides-Extra: test
Requires-Dist: flask; extra == "test"
Requires-Dist: pytest; extra == "test"
Requires-Dist: pytest-cov; extra == "test"
Requires-Dist: pytest-mock; extra == "test"
Requires-Dist: more-itertools; extra == "test"
Requires-Dist: structlog; extra == "test"
Requires-Dist: werkzeug; extra == "test"
